matrix_runner/__init__.py
matrix_runner/__main__.py
matrix_runner/_helper.py
matrix_runner/action.py
matrix_runner/axis.py
matrix_runner/command.py
matrix_runner/config.py
matrix_runner/filter.py
matrix_runner/inspect.py
matrix_runner/preferences.py
matrix_runner/report.py
matrix_runner/runner.py
python_matrix_runner-1.2.0.dist-info/LICENSE
python_matrix_runner-1.2.0.dist-info/METADATA
python_matrix_runner-1.2.0.dist-info/WHEEL
python_matrix_runner-1.2.0.dist-info/entry_points.txt
python_matrix_runner-1.2.0.dist-info/top_level.txt
python_matrix_runner-1.2.0.dist-info/RECORD
