Metadata-Version: 2.1
Name: python-matrix-runner
Version: 1.2.0
Summary: Helper to run command with matrix configurations
Home-page: https://github.com/energy6/python-matrix-runner
Author: Jonatan Antoni
Author-email: jonatan@familie-antoni.de
License: BSD 3-Clause License
Classifier: Development Status :: 5 - Production/Stable
Classifier: Intended Audience :: Developers
Classifier: License :: OSI Approved :: BSD License
Classifier: Natural Language :: English
Classifier: Operating System :: OS Independent
Classifier: Programming Language :: Python
Classifier: Programming Language :: Python :: 3
Classifier: Programming Language :: Python :: 3.8
Classifier: Programming Language :: Python :: 3.9
Classifier: Programming Language :: Python :: 3.10
Classifier: Programming Language :: Python :: 3.11
Classifier: Programming Language :: Python :: 3.12
Classifier: Topic :: Software Development :: Build Tools
Requires-Python: >=3.8
License-File: LICENSE
Requires-Dist: allpairspy ~=2.5
Requires-Dist: ansicolors ~=1.1
Requires-Dist: colorama ~=0.4
Requires-Dist: colorlog ~=6.7
Requires-Dist: filelock ~=3.12
Requires-Dist: junitparser ~=2.8
Requires-Dist: lxml ~=4.9
Requires-Dist: parameterized ~=0.9
Requires-Dist: psutil ~=5.9
Requires-Dist: tabulate ~=0.9
Provides-Extra: dev
Requires-Dist: coverage ~=6.5 ; extra == 'dev'
Requires-Dist: pylint ~=2.17 ; extra == 'dev'
Requires-Dist: restructuredtext-lint ~=1.4 ; extra == 'dev'
Requires-Dist: setuptools ~=68.2 ; extra == 'dev'
Requires-Dist: unittest-xml-reporting ~=3.2 ; extra == 'dev'
